eia_v2/__init__.py
eia_v2/client.py
eia_v2-0.2.0.dist-info/LICENSE
eia_v2-0.2.0.dist-info/METADATA
eia_v2-0.2.0.dist-info/WHEEL
eia_v2-0.2.0.dist-info/top_level.txt
eia_v2-0.2.0.dist-info/RECORD
