Metadata-Version: 2.1
Name: eia-v2
Version: 0.2.0
Summary: Client for US Energy Information Administration version2 REST API
Author: San Menra
Author-email: smenra@gmail.com
Classifier: Programming Language :: Python :: 3
Classifier: License :: OSI Approved :: MIT License
Classifier: Operating System :: OS Independent
Requires-Python: >=3.6
License-File: LICENSE
